libMHCUDA.so
libMHCUDA-2.3.0.dist-info/RECORD
libMHCUDA-2.3.0.dist-info/top_level.txt
libMHCUDA-2.3.0.dist-info/LICENSE.md
libMHCUDA-2.3.0.dist-info/METADATA
libMHCUDA-2.3.0.dist-info/WHEEL
libMHCUDA.libs/libcurand-97813df9.so.10.3.0.86
libMHCUDA.libs/libgomp-92da9020.so.1.0.0
