Metadata-Version: 2.1
Name: libMHCUDA
Version: 2.3.0
Summary: Accelerated Weighted MinHash-ing on GPU
Home-page: https://github.com/src-d/minhashcuda
Download-URL: https://github.com/src-d/minhashcuda
Author: Vadim Markovtsev
Author-email: vadim@sourced.tech
License: Apache Software License
Classifier: Development Status :: 5 - Production/Stable
Classifier: Intended Audience :: Developers
Classifier: License :: OSI Approved :: Apache Software License
Classifier: Operating System :: POSIX :: Linux
Classifier: Topic :: Scientific/Engineering :: Information Analysis
Classifier: Programming Language :: Python :: 3.10
License-File: LICENSE.md
Requires-Dist: numpy
